filer_optimizer/__init__.py
filer_optimizer/apps.py
filer_optimizer/settings.py
filer_optimizer/signals.py
filer_optimizer/utils.py
django_filer_optimizer-0.3.1.dist-info/LICENSE
django_filer_optimizer-0.3.1.dist-info/METADATA
django_filer_optimizer-0.3.1.dist-info/WHEEL
django_filer_optimizer-0.3.1.dist-info/top_level.txt
django_filer_optimizer-0.3.1.dist-info/RECORD
